Metadata-Version: 2.4
Name: pybiotk
Version: 1.3.3
Summary: pybiotk: A python toolkit for bioinformatics analysis.
Home-page: https://github.com/liqiming-whu/pybiotk
Author: liqiming_whu
Author-email: liqiming@whu.edu.cn
License: MIT
Project-URL: Documentation, https://github.com/liqiming-whu/pybiotk
Platform: any
Classifier: Development Status :: 4 - Beta
Classifier: Programming Language :: Python
License-File: LICENSE.txt
Requires-Dist: openpyxl
Requires-Dist: pandas
Requires-Dist: pysam
Requires-Dist: pyBigWig
Requires-Dist: matplotlib
Requires-Dist: scipy
Requires-Dist: rich
Provides-Extra: testing
Requires-Dist: setuptools; extra == "testing"
Requires-Dist: pytest; extra == "testing"
Requires-Dist: pytest-cov; extra == "testing"
Dynamic: license-file
